<?xml version="1.0" encoding="utf-8"?>
<EntityRelationships xmlns:xsi="http://www.w3.org/2001/XMLSchema-instance">
  <EntityRelationship Name="business_unit_mshack_coach" />
  <EntityRelationship Name="business_unit_mshack_hackevent" />
  <EntityRelationship Name="lk_mshack_coach_createdby" />
  <EntityRelationship Name="lk_mshack_coach_modifiedby" />
  <EntityRelationship Name="lk_mshack_hackevent_createdby" />
  <EntityRelationship Name="lk_mshack_hackevent_modifiedby" />
  <EntityRelationship Name="mshack_coach_HackEventId_mshack_hackevent" />
  <EntityRelationship Name="mshack_coach_SystemUserId_systemuser" />
  <EntityRelationship Name="mshack_HackTeam_mshack_Coach_mshack_Coach" />
  <EntityRelationship Name="mshack_mshack_coach_AADUserId_aaduser" />
  <EntityRelationship Name="owner_mshack_coach" />
  <EntityRelationship Name="owner_mshack_hackevent" />
  <EntityRelationship Name="team_mshack_coach" />
  <EntityRelationship Name="team_mshack_hackevent" />
  <EntityRelationship Name="user_mshack_coach" />
  <EntityRelationship Name="user_mshack_hackevent" />
</EntityRelationships>